test_helper_by_delica/__init__.py
test_helper_by_delica/test_helper_funcs.py
test_helper_by_delica-0.1.7.dist-info/METADATA
test_helper_by_delica-0.1.7.dist-info/WHEEL
test_helper_by_delica-0.1.7.dist-info/top_level.txt
test_helper_by_delica-0.1.7.dist-info/RECORD
