Metadata-Version: 2.4
Name: test_helper_by_delica
Version: 0.1.7
Summary: A Python package that simplifies the creation and execution of unittest test cases.
Author: Delica Leboe-McGowan
Author-email: Delica Leboe-McGowan <stormindustries22@outlook.com>
License-Expression: MIT
Classifier: Programming Language :: Python :: 3
Classifier: Operating System :: OS Independent
Requires-Python: >=3.9
Dynamic: author
